{
  "objectInfo" : {
    "id" : "9zCGyuhb6kEg0McIHC2AgS",
    "name" : "PullByCommitHash_CRUD_Folder",
    "type" : "Folder",
    "metadata" : {
      "modelVersion" : {
        "major" : 0,
        "minor" : 0
      },
      "repoInfo" : null,
      "contextAttributes" : [ ],
      "additionalInfo" : {
        "description" : "",
        "contentType" : "Binary",
        "documentState" : "COMPLETE"
      }
    }
  },
  "dataFileExtension" : "json",
  "updateTime" : "2023-07-26T22:51:50.907Z",
  "objectRefs" : [ ]
}